<?xml version="1.0" encoding="UTF-8"?>
<configs>
	<remove xpath="/recipes/recipe[contains(@name, 'yroCopter')]"/>
    <append xpath="/recipes">
        <recipe name="vehicle4x4TruckPlaceable" count="1" craft_time="1">
            <ingredient name="ygVehicleVoucher" count="1"/>
        </recipe>
        <recipe name="vehicleMinibikePlaceable" count="1" craft_time="1">
            <ingredient name="ygVehicleVoucher" count="1"/>
        </recipe>
        <recipe name="vehicleMotorcyclePlaceable" count="1" craft_time="1">
            <ingredient name="ygVehicleVoucher" count="1"/>
        </recipe>
</configs>